{
  "season": {
    "season_year": 2025,
    "season_position": 5,
    "season_points": 173,
    "gp_races": 18,
    "gp_points": 164,
    "gp_podiums": 5,
    "gp_top10s": 15,
    "wins": 0,
    "dnfs": 2,
    "best_grid": 1,
    "poles": 1,
    "sprint_races": 0,
    "sprint_points": 0,
    "sprint_podiums": 0,
    "sprint_poles": 0,
    "sprint_top10s": 0
  },
  "career": {
    "gp_entered": 100,
    "points": 813,
    "best_finish": "1 (x5)",
    "podiums": 23,
    "best_grid": 1,
    "poles": 18,
    "world_championships": 0,
    "dnfs": 18
  }
}